MANIFEST.in
README.rst
setup.py
collective/__init__.py
collective.itvalidators.egg-info/PKG-INFO
collective.itvalidators.egg-info/SOURCES.txt
collective.itvalidators.egg-info/dependency_links.txt
collective.itvalidators.egg-info/entry_points.txt
collective.itvalidators.egg-info/namespace_packages.txt
collective.itvalidators.egg-info/not-zip-safe
collective.itvalidators.egg-info/requires.txt
collective.itvalidators.egg-info/top_level.txt
collective/itvalidators/__init__.py
collective/itvalidators/config.py
collective/itvalidators/configure.zcml
collective/itvalidators/locales/collective.itvalidators.pot
collective/itvalidators/locales/i18n.sh
collective/itvalidators/locales/it/LC_MESSAGES/collective.itvalidators.po
collective/itvalidators/tests/__init__.py
collective/itvalidators/tests/test_validation.py
collective/itvalidators/validators/__init__.py
collective/itvalidators/validators/base_validators.py
collective/itvalidators/validators/dependency_check.py
collective/itvalidators/validators/min_chars.py
docs/HISTORY.txt
docs/INSTALL.txt
docs/LICENSE.GPL
docs/LICENSE.txt