Metadata-Version: 1.0
Name: collective.itvalidators
Version: 1.0.0
Summary: A set of Archetypes validators for Plone, some for Italian specific needs, others useful for all
Home-page: http://plone.org/products/collective.itvalidators
Author: RedTurtle Technology
Author-email: sviluppoplone@redturtle.it
License: GPL
Keywords: plone archetypes validator plonegov
Platform: UNKNOWN
Classifier: Framework :: Plone
Classifier: Framework :: Plone :: 3.3
Classifier: Framework :: Plone :: 4.0
Classifier: Framework :: Plone :: 4.1
Classifier: Framework :: Plone :: 4.2
Classifier: Programming Language :: Python
Classifier: Intended Audience :: Developers
Classifier: Development Status :: 5 - Production/Stable
